README.md
setup.cfg
setup.py
thai2transformers/__init__.py
thai2transformers/auto.py
thai2transformers/conf.py
thai2transformers/datasets.py
thai2transformers/finetuners.py
thai2transformers/helper.py
thai2transformers/metrics.py
thai2transformers/mmap.py
thai2transformers/models.py
thai2transformers/preprocess.py
thai2transformers/tokenizers.py
thai2transformers/utils.py
thai2transformers.egg-info/PKG-INFO
thai2transformers.egg-info/SOURCES.txt
thai2transformers.egg-info/dependency_links.txt
thai2transformers.egg-info/not-zip-safe
thai2transformers.egg-info/requires.txt
thai2transformers.egg-info/top_level.txt