Metadata-Version: 2.1
Name: thai2transformers
Version: 0.1.2
Summary: Pretraining transformer based Thai language models
Home-page: https://github.com/vistec-AI/thai2transformers
Author: VISTEC-depa AI Research Institute of Thailand
Author-email: 
License: Apache Software License 2.0
Project-URL: Documentation, https://github.com/vistec-AI/thai2transformers
Project-URL: Tutorials, https://colab.research.google.com/drive/1Kbk6sBspZLwcnOE61adAQo30xxqOQ9ko?usp=sharing
Project-URL: Source Code, https://github.com/vistec-AI/thai2transformers
Project-URL: Bug Tracker, https://github.com/vistec-AI/thai2transformers/issues
Keywords: thainlp,NLP,natural language processing,text analytics,text processing,localization,computational linguistics,ThaiNLP,Thai NLP,Thai language
Platform: UNKNOWN
Classifier: Development Status :: 3 - Alpha
Classifier: Programming Language :: Python :: 3
Classifier: Intended Audience :: Developers
Classifier: License :: OSI Approved :: Apache Software License
Classifier: Natural Language :: Thai
Classifier: Topic :: Scientific/Engineering :: Artificial Intelligence
Classifier: Topic :: Text Processing
Classifier: Topic :: Text Processing :: General
Classifier: Topic :: Text Processing :: Linguistic
Requires-Python: >=3.6
